[{"description":"基于任务负载的高可用IOT规则引擎，动态启动、停止任务和传参，实时监控任务状态","fullName":"ziapple/iot-rule-engine","language":"Java","license":{"key":"","name":"","url":""},"pushedAt":"2019-03-03T11:40:17Z","stargazersCount":56,"url":"https://github.com/ziapple/iot-rule-engine"},{"description":"","fullName":"enableiot/iotanalytics-rule-engine","language":"Python","license":{"key":"apache-2.0","name":"Apache License 2.0","url":"https://api.github.com/licenses/apache-2.0"},"pushedAt":"2024-06-25T17:31:02Z","stargazersCount":3,"url":"https://github.com/enableiot/iotanalytics-rule-engine"},{"description":"Personal IOT Rule Engine (Experimental)","fullName":"a15lam/jarvis","language":"PHP","license":{"key":"apache-2.0","name":"Apache License 2.0","url":"https://api.github.com/licenses/apache-2.0"},"pushedAt":"2019-05-16T11:16:08Z","stargazersCount":2,"url":"https://github.com/a15lam/jarvis"},{"description":"IoT Rule Engine","fullName":"UdamLiyanage/rule-engine-deprecated","language":"Go","license":{"key":"","name":"","url":""},"pushedAt":"2020-01-31T07:36:51Z","stargazersCount":1,"url":"https://github.com/UdamLiyanage/rule-engine-deprecated"},{"description":"","fullName":"OiJs/iot-rule-engine","language":"Java","license":{"key":"","name":"","url":""},"pushedAt":"2026-05-08T05:37:59Z","stargazersCount":0,"url":"https://github.com/OiJs/iot-rule-engine"},{"description":"","fullName":"Basillica/iot-rule-engine","language":"Rust","license":{"key":"","name":"","url":""},"pushedAt":"2026-01-09T16:16:17Z","stargazersCount":0,"url":"https://github.com/Basillica/iot-rule-engine"},{"description":"IoT Rule Engine in Golang","fullName":"Rything/iot-rule-engine-1","language":"","license":{"key":"","name":"","url":""},"pushedAt":"2019-04-10T15:47:05Z","stargazersCount":0,"url":"https://github.com/Rything/iot-rule-engine-1"},{"description":"An example project showing how to set up AWS Lambda Powertools for Typescript to help understand the behavior of the AWS IoT Rules Engine with AWS Lambda integration.","fullName":"aws-iot-builder-tools/aws-iot-rules-engine-to-lambda-sample","language":"JavaScript","license":{"key":"mit-0","name":"MIT No Attribution","url":"https://api.github.com/licenses/mit-0"},"pushedAt":"2026-04-10T03:46:23Z","stargazersCount":0,"url":"https://github.com/aws-iot-builder-tools/aws-iot-rules-engine-to-lambda-sample"},{"description":"Several way to write IoT rule engine","fullName":"linonetwo/rule-engine-playground","language":"Elixir","license":{"key":"","name":"","url":""},"pushedAt":"2023-12-15T08:19:19Z","stargazersCount":1,"url":"https://github.com/linonetwo/rule-engine-playground"},{"description":"Mnubo sample lambda function in Python to be called from the AWS IoT rules engine.","fullName":"sebastienc/lambda-mnubo-python","language":"Python","license":{"key":"apache-2.0","name":"Apache License 2.0","url":"https://api.github.com/licenses/apache-2.0"},"pushedAt":"2017-12-08T16:16:47Z","stargazersCount":0,"url":"https://github.com/sebastienc/lambda-mnubo-python"}]
